netprocmon/__init__.py
netprocmon/monitor.py
netprocmon-0.0.1rc7.dist-info/LICENSE.txt
netprocmon-0.0.1rc7.dist-info/METADATA
netprocmon-0.0.1rc7.dist-info/WHEEL
netprocmon-0.0.1rc7.dist-info/top_level.txt
netprocmon-0.0.1rc7.dist-info/RECORD
