Metadata-Version: 2.1
Name: netprocmon
Version: 0.0.1rc7
Summary: Network Process Monitor is a Python API to monitor process traffic
Home-page: https://pypi.python.org/pypi/netprocmon
Author: Henrik Ankersoe
Author-email: henrik@diblo.dk
License: GPL v3
Platform: UNKNOWN
Classifier: Development Status :: 4 - Beta
Classifier: Intended Audience :: Developers
Classifier: Topic :: Software Development :: Build Tools
Classifier: Topic :: Software Development :: Libraries :: Python Modules
Classifier: License :: OSI Approved :: GNU General Public License v3 (GPLv3)
Classifier: Programming Language :: Python :: 2.7
